bling/__init__.py
bling/ast.py
bling/grammar.py
bling/interpreter.py
bling-0.0.3.dist-info/DESCRIPTION.rst
bling-0.0.3.dist-info/METADATA
bling-0.0.3.dist-info/RECORD
bling-0.0.3.dist-info/WHEEL
bling-0.0.3.dist-info/metadata.json
bling-0.0.3.dist-info/top_level.txt
