Metadata-Version: 2.0
Name: bling
Version: 0.0.3
Summary: Bling is a simple languagee for controlling LED strips.
Home-page: https://github.com/ungood/bling
Author: Jason Walker
Author-email: ungood@onetrue.name
License: UNKNOWN
Platform: UNKNOWN
Classifier: Development Status :: 2 - Pre-Alpha
Classifier: Programming Language :: Python
Classifier: Programming Language :: Python :: 2
Classifier: Programming Language :: Python :: 2.7
Classifier: Programming Language :: Python :: 3
Classifier: Programming Language :: Python :: 3.4
Requires-Dist: colour
Requires-Dist: pyparsing
